vineyard-0.24.2.dist-info/WHEEL
vineyard-0.24.2.dist-info/top_level.txt
vineyard-0.24.2.dist-info/LICENSE
vineyard-0.24.2.dist-info/NOTICE.txt
vineyard-0.24.2.dist-info/METADATA
vineyard-0.24.2.dist-info/RECORD
vineyard-0.24.2.dist-info/entry_points.txt
vineyard/__main__.py
vineyard/version.py
vineyard/libvineyard_internal_registry.so
vineyard/__init__.py
vineyard/py.typed
vineyard/ctl.py
vineyard/_C.pyi
vineyard/_C.cpython-311-x86_64-linux-gnu.so
vineyard/conftest.py
vineyard/launcher/__init__.py
vineyard/launcher/launcher.py
vineyard/launcher/script.py
vineyard/contrib/__init__.py
vineyard/shared_memory/__init__.py
vineyard/shared_memory/shared_memory.py
vineyard/shared_memory/tests/test_shared_memory.py
vineyard/shared_memory/tests/__init__.py
vineyard/csi/__init__.py
vineyard/io/utils.py
vineyard/io/core.py
vineyard/io/__init__.py
vineyard/io/stream.py
vineyard/io/byte.py
vineyard/io/recordbatch.py
vineyard/io/serialization.py
vineyard/io/dataframe.py
vineyard/io/parallel.py
vineyard/io/tests/__init__.py
vineyard/io/tests/test_stream.py
vineyard/io/scripts/__init__.py
vineyard/core/driver.py
vineyard/core/utils.py
vineyard/core/client.py
vineyard/core/__init__.py
vineyard/core/resolver.py
vineyard/core/builder.py
vineyard/core/tests/__init__.py
vineyard/core/tests/test_client.py
vineyard/core/tests/test_rpc_client.py
vineyard/core/tests/test_context.py
vineyard/core/codegen/parsing.py
vineyard/core/codegen/__main__.py
vineyard/core/codegen/java.py
vineyard/core/codegen/__init__.py
vineyard/core/codegen/python.py
vineyard/core/codegen/cpp.py
vineyard/core/codegen/main.py
vineyard/deploy/utils.py
vineyard/deploy/etcd.py
vineyard/deploy/vineyard.yaml.tpl
vineyard/deploy/__main__.py
vineyard/deploy/etcd.yaml
vineyard/deploy/__init__.py
vineyard/deploy/local.py
vineyard/deploy/kubernetes.py
vineyard/deploy/ctl.py
vineyard/deploy/distributed.py
vineyard/deploy/_cobra.py
vineyard/deploy/tests/test_migration.py
vineyard/deploy/tests/test_local.py
vineyard/deploy/tests/__init__.py
vineyard/deploy/tests/test_vineyardd_failure.py
vineyard/deploy/tests/test_distributed.py
vineyard/bdist/__init__.py
vineyard/drivers/__init__.py
vineyard/systemd/__main__.py
