Metadata-Version: 2.1
Name: vineyard
Version: 0.24.2
Summary: An in-memory immutable data manager
Home-page: https://v6d.io
Author: The vineyard team
Author-email: developers@v6d.io
License: Apache License 2.0
Project-URL: Documentation, https://v6d.io
Project-URL: Source, https://github.com/v6d-io/v6d
Project-URL: Tracker, https://github.com/v6d-io/v6d/issues
Platform: POSIX
Platform: MacOS
Classifier: Development Status :: 5 - Production/Stable
Classifier: Intended Audience :: Developers
Classifier: Intended Audience :: Science/Research
Classifier: License :: OSI Approved :: Apache Software License
Classifier: Topic :: Software Development :: Libraries
Classifier: Topic :: System :: Distributed Computing
Classifier: Operating System :: MacOS :: MacOS X
Classifier: Operating System :: POSIX
Classifier: Programming Language :: Python
Classifier: Programming Language :: Python :: 3
Classifier: Programming Language :: Python :: 3.6
Classifier: Programming Language :: Python :: 3.7
Classifier: Programming Language :: Python :: 3.8
Classifier: Programming Language :: Python :: 3.9
Classifier: Programming Language :: Python :: 3.10
Classifier: Programming Language :: Python :: 3.11
License-File: LICENSE
License-File: NOTICE.txt
Requires-Dist: argcomplete
Requires-Dist: click
Requires-Dist: etcd-distro
Requires-Dist: lazy-import
Requires-Dist: makefun
Requires-Dist: numpy (>=1.18.5)
Requires-Dist: psutil
Requires-Dist: pyarrow
Requires-Dist: pyyaml
Requires-Dist: setuptools
Requires-Dist: sortedcontainers
Requires-Dist: treelib
Requires-Dist: vineyard-bdist (==0.24.2)
Requires-Dist: pandas (<1.0.0) ; python_version < "3.6"
Requires-Dist: pandas (<1.2.0) ; python_version < "3.7"
Requires-Dist: pickle5 ; python_version <= "3.7"
Requires-Dist: shared-memory38 ; python_version <= "3.7"
Requires-Dist: pandas (>=1.0.0) ; python_version >= "3.7"
Provides-Extra: dev
Requires-Dist: black (>=22.3.0) ; extra == 'dev'
Requires-Dist: breathe ; extra == 'dev'
Requires-Dist: docutils (==0.20.1) ; extra == 'dev'
Requires-Dist: flake8 (>=4.0.1) ; extra == 'dev'
Requires-Dist: flake8-comprehensions ; extra == 'dev'
Requires-Dist: flake8-logging-format ; extra == 'dev'
Requires-Dist: furo ; extra == 'dev'
Requires-Dist: isort (>=5.10.1) ; extra == 'dev'
Requires-Dist: jinja2 (>=3.1.0) ; extra == 'dev'
Requires-Dist: libclang ; extra == 'dev'
Requires-Dist: linkify-it-py ; extra == 'dev'
Requires-Dist: myst-parser (>=0.13.0) ; extra == 'dev'
Requires-Dist: nbsphinx ; extra == 'dev'
Requires-Dist: pygments (>=2.4.1) ; extra == 'dev'
Requires-Dist: pytest (<8.0.0) ; extra == 'dev'
Requires-Dist: pytest-benchmark ; extra == 'dev'
Requires-Dist: pytest-cases ; extra == 'dev'
Requires-Dist: pytest-datafiles ; extra == 'dev'
Requires-Dist: pytest-timeout ; extra == 'dev'
Requires-Dist: sphinx (>=7.1.2) ; extra == 'dev'
Requires-Dist: sphinx-copybutton ; extra == 'dev'
Requires-Dist: sphinx-panels ; extra == 'dev'
Requires-Dist: sphinxemoji ; extra == 'dev'
Requires-Dist: sphinxext-opengraph ; extra == 'dev'
Requires-Dist: google-re2 (==1.1) ; extra == 'dev'
Provides-Extra: extra
Requires-Dist: scipy ; extra == 'extra'
Requires-Dist: polars ; extra == 'extra'
Provides-Extra: kubernetes
Requires-Dist: kubernetes ; extra == 'kubernetes'
